Metadata-Version: 2.1
Name: simpleaichat
Version: 0.1.1
Summary: A Python package for easily interfacing with chat apps, with robust features and minimal code complexity.
Home-page: https://github.com/minimaxir/simpleaichat
Author: Max Woolf
Author-email: max@minimaxir.com
License: MIT
Keywords: chatgpt,openai,text generation,ai
Platform: UNKNOWN
Requires-Python: >=3.8
License-File: LICENSE
